{
  "configId": "mtt8_chipev_10bb_ante1",
  "lineId": "bb_call_vs_btn",
  "actions": [
    "fold",
    "call"
  ],
  "classFrequencies": {
    "0": [
      0.0156,
      0.9844
    ],
    "1": [
      0.0113,
      0.9887
    ],
    "2": [
      0.0105,
      0.9895
    ],
    "3": [
      0.0078,
      0.9922
    ],
    "4": [
      0.0081,
      0.9919
    ],
    "5": [
      0.0058,
      0.9942
    ],
    "6": [
      0.0059,
      0.9941
    ],
    "7": [
      0.0051,
      0.9949
    ],
    "8": [
      0.0036,
      0.9964
    ],
    "9": [
      0.0031,
      0.9969
    ],
    "10": [
      0.0026,
      0.9974
    ],
    "11": [
      0.0015,
      0.9985
    ],
    "12": [
      0,
      1
    ],
    "13": [
      0.9984,
      0.0016
    ],
    "14": [
      0.9967,
      0.0033
    ],
    "15": [
      0.9856,
      0.0144
    ],
    "16": [
      0.9907,
      0.0093
    ],
    "17": [
      0.9813,
      0.0187
    ],
    "18": [
      0.9214,
      0.0786
    ],
    "19": [
      0.995,
      0.005
    ],
    "20": [
      0.9887,
      0.0113
    ],
    "21": [
      0.9606,
      0.0394
    ],
    "22": [
      0.8278,
      0.1722
    ],
    "23": [
      0.9928,
      0.0072
    ],
    "24": [
      0.99,
      0.01
    ],
    "25": [
      0.9701,
      0.0299
    ],
    "26": [
      0.9192,
      0.0808
    ],
    "27": [
      0.1627,
      0.8373
    ],
    "28": [
      0.9931,
      0.0069
    ],
    "29": [
      0.9881,
      0.0119
    ],
    "30": [
      0.9751,
      0.0249
    ],
    "31": [
      0.9551,
      0.0449
    ],
    "32": [
      0.7752,
      0.2248
    ],
    "33": [
      0.0946,
      0.9054
    ],
    "34": [
      0.9891,
      0.0109
    ],
    "35": [
      0.986,
      0.014
    ],
    "36": [
      0.9792,
      0.0208
    ],
    "37": [
      0.965,
      0.035
    ],
    "38": [
      0.8093,
      0.1907
    ],
    "39": [
      0.2486,
      0.7514
    ],
    "40": [
      0.0814,
      0.9186
    ],
    "41": [
      0.9858,
      0.0142
    ],
    "42": [
      0.9789,
      0.0211
    ],
    "43": [
      0.9703,
      0.0297
    ],
    "44": [
      0.9706,
      0.0294
    ],
    "45": [
      0.9,
      0.1
    ],
    "46": [
      0.317,
      0.683
    ],
    "47": [
      0.0601,
      0.9399
    ],
    "48": [
      0.0323,
      0.9677
    ],
    "49": [
      0.9711,
      0.0289
    ],
    "50": [
      0.9615,
      0.0385
    ],
    "51": [
      0.9316,
      0.0684
    ],
    "52": [
      0.906,
      0.094
    ],
    "53": [
      0.8721,
      0.1279
    ],
    "54": [
      0.2223,
      0.7777
    ],
    "55": [
      0.1242,
      0.8758
    ],
    "56": [
      0.043,
      0.957
    ],
    "57": [
      0.0197,
      0.9803
    ],
    "58": [
      0.9328,
      0.0672
    ],
    "59": [
      0.8392,
      0.1608
    ],
    "60": [
      0.7526,
      0.2474
    ],
    "61": [
      0.2209,
      0.7791
    ],
    "62": [
      0.103,
      0.897
    ],
    "63": [
      0.1477,
      0.8523
    ],
    "64": [
      0.0592,
      0.9408
    ],
    "65": [
      0.0283,
      0.9717
    ],
    "66": [
      0.0158,
      0.9842
    ],
    "67": [
      0.0133,
      0.9867
    ],
    "68": [
      0.0932,
      0.9068
    ],
    "69": [
      0.0565,
      0.9435
    ],
    "70": [
      0.0531,
      0.9469
    ],
    "71": [
      0.0385,
      0.9615
    ],
    "72": [
      0.034,
      0.966
    ],
    "73": [
      0.0268,
      0.9732
    ],
    "74": [
      0.0261,
      0.9739
    ],
    "75": [
      0.0151,
      0.9849
    ],
    "76": [
      0.011,
      0.989
    ],
    "77": [
      0.0103,
      0.9897
    ],
    "78": [
      0.0079,
      0.9921
    ],
    "79": [
      0.0134,
      0.9866
    ],
    "80": [
      0.0127,
      0.9873
    ],
    "81": [
      0.01,
      0.99
    ],
    "82": [
      0.0093,
      0.9907
    ],
    "83": [
      0.0112,
      0.9888
    ],
    "84": [
      0.0088,
      0.9912
    ],
    "85": [
      0.0085,
      0.9915
    ],
    "86": [
      0.0073,
      0.9927
    ],
    "87": [
      0.0057,
      0.9943
    ],
    "88": [
      0.0041,
      0.9959
    ],
    "89": [
      0.0035,
      0.9965
    ],
    "90": [
      0.0016,
      0.9984
    ],
    "91": [
      0.9996,
      0.0004
    ],
    "92": [
      0.9995,
      0.0005
    ],
    "93": [
      0.9976,
      0.0024
    ],
    "94": [
      0.9992,
      0.0008
    ],
    "95": [
      0.9969,
      0.0031
    ],
    "96": [
      0.993,
      0.007
    ],
    "97": [
      0.9988,
      0.0012
    ],
    "98": [
      0.9973,
      0.0027
    ],
    "99": [
      0.9946,
      0.0054
    ],
    "100": [
      0.9908,
      0.0092
    ],
    "101": [
      0.9986,
      0.0014
    ],
    "102": [
      0.9971,
      0.0029
    ],
    "103": [
      0.9951,
      0.0049
    ],
    "104": [
      0.9926,
      0.0074
    ],
    "105": [
      0.9836,
      0.0164
    ],
    "106": [
      0.9981,
      0.0019
    ],
    "107": [
      0.9967,
      0.0033
    ],
    "108": [
      0.9962,
      0.0038
    ],
    "109": [
      0.9927,
      0.0073
    ],
    "110": [
      0.9873,
      0.0127
    ],
    "111": [
      0.9754,
      0.0246
    ],
    "112": [
      0.9973,
      0.0027
    ],
    "113": [
      0.9962,
      0.0038
    ],
    "114": [
      0.9955,
      0.0045
    ],
    "115": [
      0.9933,
      0.0067
    ],
    "116": [
      0.9891,
      0.0109
    ],
    "117": [
      0.9814,
      0.0186
    ],
    "118": [
      0.9524,
      0.0476
    ],
    "119": [
      0.9957,
      0.0043
    ],
    "120": [
      0.9952,
      0.0048
    ],
    "121": [
      0.9934,
      0.0066
    ],
    "122": [
      0.9926,
      0.0074
    ],
    "123": [
      0.99,
      0.01
    ],
    "124": [
      0.98,
      0.02
    ],
    "125": [
      0.9503,
      0.0497
    ],
    "126": [
      0.4672,
      0.5328
    ],
    "127": [
      0.9936,
      0.0064
    ],
    "128": [
      0.9929,
      0.0071
    ],
    "129": [
      0.9911,
      0.0089
    ],
    "130": [
      0.9896,
      0.0104
    ],
    "131": [
      0.9888,
      0.0112
    ],
    "132": [
      0.9788,
      0.0212
    ],
    "133": [
      0.9552,
      0.0448
    ],
    "134": [
      0.2939,
      0.7061
    ],
    "135": [
      0.0355,
      0.9645
    ],
    "136": [
      0.9869,
      0.0131
    ],
    "137": [
      0.9864,
      0.0136
    ],
    "138": [
      0.9822,
      0.0178
    ],
    "139": [
      0.9769,
      0.0231
    ],
    "140": [
      0.9689,
      0.0311
    ],
    "141": [
      0.9651,
      0.0349
    ],
    "142": [
      0.8542,
      0.1458
    ],
    "143": [
      0.1109,
      0.8891
    ],
    "144": [
      0.0255,
      0.9745
    ],
    "145": [
      0.0151,
      0.9849
    ],
    "146": [
      0.9671,
      0.0329
    ],
    "147": [
      0.9464,
      0.0536
    ],
    "148": [
      0.9172,
      0.0828
    ],
    "149": [
      0.6938,
      0.3062
    ],
    "150": [
      0.1856,
      0.8144
    ],
    "151": [
      0.1085,
      0.8915
    ],
    "152": [
      0.0392,
      0.9608
    ],
    "153": [
      0.0181,
      0.9819
    ],
    "154": [
      0.0104,
      0.9896
    ],
    "155": [
      0.0081,
      0.9919
    ],
    "156": [
      0.007,
      0.993
    ],
    "157": [
      0.0147,
      0.9853
    ],
    "158": [
      0.0126,
      0.9874
    ],
    "159": [
      0.0107,
      0.9893
    ],
    "160": [
      0.0101,
      0.9899
    ],
    "161": [
      0.0108,
      0.9892
    ],
    "162": [
      0.0081,
      0.9919
    ],
    "163": [
      0.007,
      0.993
    ],
    "164": [
      0.0063,
      0.9937
    ],
    "165": [
      0.0045,
      0.9955
    ],
    "166": [
      0.0033,
      0.9967
    ],
    "167": [
      0.0024,
      0.9976
    ],
    "168": [
      0.0015,
      0.9985
    ]
  }
}