{
  "configId": "mtt8_chipev_12bb_ante0",
  "lineId": "sb_call_vs_utg1",
  "actions": [
    "fold",
    "call"
  ],
  "classFrequencies": {
    "0": [
      0.944,
      0.056
    ],
    "1": [
      0.9479,
      0.0521
    ],
    "2": [
      0.8529,
      0.1471
    ],
    "3": [
      0.7302,
      0.2698
    ],
    "4": [
      0.3316,
      0.6684
    ],
    "5": [
      0.1459,
      0.8541
    ],
    "6": [
      0.0513,
      0.9487
    ],
    "7": [
      0.046,
      0.954
    ],
    "8": [
      0.0227,
      0.9773
    ],
    "9": [
      0.017,
      0.983
    ],
    "10": [
      0.013,
      0.987
    ],
    "11": [
      0.0086,
      0.9914
    ],
    "12": [
      0.0036,
      0.9964
    ],
    "13": [
      0.9796,
      0.0204
    ],
    "14": [
      0.9777,
      0.0223
    ],
    "15": [
      0.9697,
      0.0303
    ],
    "16": [
      0.9759,
      0.0241
    ],
    "17": [
      0.975,
      0.025
    ],
    "18": [
      0.9647,
      0.0353
    ],
    "19": [
      0.9803,
      0.0197
    ],
    "20": [
      0.9746,
      0.0254
    ],
    "21": [
      0.9702,
      0.0298
    ],
    "22": [
      0.9683,
      0.0317
    ],
    "23": [
      0.9752,
      0.0248
    ],
    "24": [
      0.9806,
      0.0194
    ],
    "25": [
      0.9695,
      0.0305
    ],
    "26": [
      0.9715,
      0.0285
    ],
    "27": [
      0.9561,
      0.0439
    ],
    "28": [
      0.9766,
      0.0234
    ],
    "29": [
      0.9777,
      0.0223
    ],
    "30": [
      0.9716,
      0.0284
    ],
    "31": [
      0.9697,
      0.0303
    ],
    "32": [
      0.962,
      0.038
    ],
    "33": [
      0.9623,
      0.0377
    ],
    "34": [
      0.979,
      0.021
    ],
    "35": [
      0.9795,
      0.0205
    ],
    "36": [
      0.9762,
      0.0238
    ],
    "37": [
      0.9667,
      0.0333
    ],
    "38": [
      0.9636,
      0.0364
    ],
    "39": [
      0.9558,
      0.0442
    ],
    "40": [
      0.9621,
      0.0379
    ],
    "41": [
      0.9819,
      0.0181
    ],
    "42": [
      0.9717,
      0.0283
    ],
    "43": [
      0.9714,
      0.0286
    ],
    "44": [
      0.9728,
      0.0272
    ],
    "45": [
      0.9638,
      0.0362
    ],
    "46": [
      0.963,
      0.037
    ],
    "47": [
      0.9656,
      0.0344
    ],
    "48": [
      0.919,
      0.081
    ],
    "49": [
      0.9755,
      0.0245
    ],
    "50": [
      0.9705,
      0.0295
    ],
    "51": [
      0.9662,
      0.0338
    ],
    "52": [
      0.9732,
      0.0268
    ],
    "53": [
      0.9772,
      0.0228
    ],
    "54": [
      0.9619,
      0.0381
    ],
    "55": [
      0.9474,
      0.0526
    ],
    "56": [
      0.9513,
      0.0487
    ],
    "57": [
      0.8903,
      0.1097
    ],
    "58": [
      0.9727,
      0.0273
    ],
    "59": [
      0.9716,
      0.0284
    ],
    "60": [
      0.9627,
      0.0373
    ],
    "61": [
      0.9664,
      0.0336
    ],
    "62": [
      0.9631,
      0.0369
    ],
    "63": [
      0.9479,
      0.0521
    ],
    "64": [
      0.9582,
      0.0418
    ],
    "65": [
      0.9433,
      0.0567
    ],
    "66": [
      0.8996,
      0.1004
    ],
    "67": [
      0.9146,
      0.0854
    ],
    "68": [
      0.9643,
      0.0357
    ],
    "69": [
      0.956,
      0.044
    ],
    "70": [
      0.9571,
      0.0429
    ],
    "71": [
      0.9622,
      0.0378
    ],
    "72": [
      0.9568,
      0.0432
    ],
    "73": [
      0.9492,
      0.0508
    ],
    "74": [
      0.9261,
      0.0739
    ],
    "75": [
      0.9217,
      0.0783
    ],
    "76": [
      0.7495,
      0.2505
    ],
    "77": [
      0.7605,
      0.2395
    ],
    "78": [
      0.5029,
      0.4971
    ],
    "79": [
      0.9239,
      0.0761
    ],
    "80": [
      0.9181,
      0.0819
    ],
    "81": [
      0.8493,
      0.1507
    ],
    "82": [
      0.8443,
      0.1557
    ],
    "83": [
      0.8867,
      0.1133
    ],
    "84": [
      0.6953,
      0.3047
    ],
    "85": [
      0.6942,
      0.3058
    ],
    "86": [
      0.2072,
      0.7928
    ],
    "87": [
      0.1017,
      0.8983
    ],
    "88": [
      0.0494,
      0.9506
    ],
    "89": [
      0.0289,
      0.9711
    ],
    "90": [
      0.0186,
      0.9814
    ],
    "91": [
      0.9909,
      0.0091
    ],
    "92": [
      0.9902,
      0.0098
    ],
    "93": [
      0.9872,
      0.0128
    ],
    "94": [
      0.9897,
      0.0103
    ],
    "95": [
      0.9895,
      0.0105
    ],
    "96": [
      0.9856,
      0.0144
    ],
    "97": [
      0.9907,
      0.0093
    ],
    "98": [
      0.9906,
      0.0094
    ],
    "99": [
      0.9871,
      0.0129
    ],
    "100": [
      0.9822,
      0.0178
    ],
    "101": [
      0.992,
      0.008
    ],
    "102": [
      0.9906,
      0.0094
    ],
    "103": [
      0.9901,
      0.0099
    ],
    "104": [
      0.9864,
      0.0136
    ],
    "105": [
      0.9848,
      0.0152
    ],
    "106": [
      0.9909,
      0.0091
    ],
    "107": [
      0.9916,
      0.0084
    ],
    "108": [
      0.9905,
      0.0095
    ],
    "109": [
      0.9882,
      0.0118
    ],
    "110": [
      0.9879,
      0.0121
    ],
    "111": [
      0.9847,
      0.0153
    ],
    "112": [
      0.9916,
      0.0084
    ],
    "113": [
      0.9907,
      0.0093
    ],
    "114": [
      0.9891,
      0.0109
    ],
    "115": [
      0.99,
      0.01
    ],
    "116": [
      0.9864,
      0.0136
    ],
    "117": [
      0.9871,
      0.0129
    ],
    "118": [
      0.983,
      0.017
    ],
    "119": [
      0.9896,
      0.0104
    ],
    "120": [
      0.9893,
      0.0107
    ],
    "121": [
      0.9885,
      0.0115
    ],
    "122": [
      0.9891,
      0.0109
    ],
    "123": [
      0.9878,
      0.0122
    ],
    "124": [
      0.9879,
      0.0121
    ],
    "125": [
      0.9851,
      0.0149
    ],
    "126": [
      0.9801,
      0.0199
    ],
    "127": [
      0.9891,
      0.0109
    ],
    "128": [
      0.9893,
      0.0107
    ],
    "129": [
      0.9887,
      0.0113
    ],
    "130": [
      0.9889,
      0.0111
    ],
    "131": [
      0.9878,
      0.0122
    ],
    "132": [
      0.9868,
      0.0132
    ],
    "133": [
      0.9809,
      0.0191
    ],
    "134": [
      0.9781,
      0.0219
    ],
    "135": [
      0.9699,
      0.0301
    ],
    "136": [
      0.9892,
      0.0108
    ],
    "137": [
      0.9872,
      0.0128
    ],
    "138": [
      0.9891,
      0.0109
    ],
    "139": [
      0.9872,
      0.0128
    ],
    "140": [
      0.9874,
      0.0126
    ],
    "141": [
      0.9848,
      0.0152
    ],
    "142": [
      0.9833,
      0.0167
    ],
    "143": [
      0.9729,
      0.0271
    ],
    "144": [
      0.9715,
      0.0285
    ],
    "145": [
      0.9678,
      0.0322
    ],
    "146": [
      0.9873,
      0.0127
    ],
    "147": [
      0.9873,
      0.0127
    ],
    "148": [
      0.9841,
      0.0159
    ],
    "149": [
      0.9827,
      0.0173
    ],
    "150": [
      0.9819,
      0.0181
    ],
    "151": [
      0.9842,
      0.0158
    ],
    "152": [
      0.981,
      0.019
    ],
    "153": [
      0.9726,
      0.0274
    ],
    "154": [
      0.9444,
      0.0556
    ],
    "155": [
      0.9368,
      0.0632
    ],
    "156": [
      0.8441,
      0.1559
    ],
    "157": [
      0.9753,
      0.0247
    ],
    "158": [
      0.9734,
      0.0266
    ],
    "159": [
      0.9702,
      0.0298
    ],
    "160": [
      0.957,
      0.043
    ],
    "161": [
      0.9534,
      0.0466
    ],
    "162": [
      0.9421,
      0.0579
    ],
    "163": [
      0.9371,
      0.0629
    ],
    "164": [
      0.9004,
      0.0996
    ],
    "165": [
      0.3634,
      0.6366
    ],
    "166": [
      0.0795,
      0.9205
    ],
    "167": [
      0.0228,
      0.9772
    ],
    "168": [
      0.0141,
      0.9859
    ]
  }
}